mmxc/__init__.py
mmxc/log.py
mmxc/rect.py
mmxc-0.1.4.dist-info/METADATA
mmxc-0.1.4.dist-info/WHEEL
mmxc-0.1.4.dist-info/top_level.txt
mmxc-0.1.4.dist-info/RECORD
